abridge/__init__.py
abridge/cli.py
abridge/processor.py
abridge/ui.py
abridge-0.1.4.dist-info/entry_points.txt
abridge-0.1.4.dist-info/LICENSE
abridge-0.1.4.dist-info/WHEEL
abridge-0.1.4.dist-info/METADATA
abridge-0.1.4.dist-info/RECORD
